test/Dockerfile
test/TestCred.json
test/__init__.py
test/issueCred.py
test/requestProof.py
test/run.sh
test/testHolder.py
test/testIssuer.py
test/testSequence.py
test/volumeTest.py
vonx/__init__.py
vonx/version.py
vonx/common/__init__.py
vonx/common/config.py
vonx/common/dependencies.py
vonx/common/eventloop.py
vonx/common/exchange.py
vonx/common/manager.py
vonx/common/service.py
vonx/common/util.py
vonx/config/__init__.py
vonx/config/logging.yml
vonx/config/schemas.yml
vonx/config/settings.yml
vonx/indy/__init__.py
vonx/indy/client.py
vonx/indy/config.py
vonx/indy/connection.py
vonx/indy/errors.py
vonx/indy/manager.py
vonx/indy/messages.py
vonx/indy/service.py
vonx/indy/tob.py
vonx/templates/index.html
vonx/web/__init__.py
vonx/web/headers.py
vonx/web/helpers.py
vonx/web/process.py
vonx/web/render.py
vonx/web/routes.py
vonx/web/view_helpers.py
vonx/web/views.py
vonx-1.4.6.dist-info/LICENSE.txt
vonx-1.4.6.dist-info/METADATA
vonx-1.4.6.dist-info/WHEEL
vonx-1.4.6.dist-info/top_level.txt
vonx-1.4.6.dist-info/RECORD
