Metadata-Version: 2.1
Name: vonx
Version: 1.4.6
Summary: VON-X Connector
Home-page: https://github.com/PSPC-SPAC-buyandsell/von-x/
Author: PSPC-SPAC
Author-email: andrew@1crm.com
License: Apache Software License
Download-URL: https://github.com/PSPC-SPAC-buyandsell/von-x/archive/v1.4.6.tar.gz
Keywords: verified-organizations-network,VON,TheOrgBook,Hyperledger,Indy,HTTP
Platform: UNKNOWN
Classifier: Development Status :: 5 - Production/Stable
Classifier: Intended Audience :: Developers
Classifier: Topic :: Internet :: WWW/HTTP
Classifier: Topic :: Software Development :: Libraries :: Python Modules
Classifier: License :: OSI Approved :: Apache Software License
Classifier: Programming Language :: Python :: 3.5
Classifier: Programming Language :: Python :: 3.6
Requires-Python: >=3.5.3
Requires-Dist: aiohttp (~=3.3.0)
Requires-Dist: aiohttp-jinja2 (~=1.1.0)
Requires-Dist: didauth (==1.2.3)
Requires-Dist: PyYAML
Requires-Dist: networkx (<3von-anchor==1.6.41,>=2.2)
